azure/cosmos/__init__.py
azure/cosmos/_auth_policy.py
azure/cosmos/_base.py
azure/cosmos/_constants.py
azure/cosmos/_container_recreate_retry_policy.py
azure/cosmos/_cosmos_client_connection.py
azure/cosmos/_cosmos_http_logging_policy.py
azure/cosmos/_cosmos_integers.py
azure/cosmos/_cosmos_murmurhash3.py
azure/cosmos/_cosmos_responses.py
azure/cosmos/_default_retry_policy.py
azure/cosmos/_endpoint_discovery_retry_policy.py
azure/cosmos/_global_endpoint_manager.py
azure/cosmos/_gone_retry_policy.py
azure/cosmos/_location_cache.py
azure/cosmos/_partition.py
azure/cosmos/_query_iterable.py
azure/cosmos/_range.py
azure/cosmos/_range_partition_resolver.py
azure/cosmos/_request_object.py
azure/cosmos/_resource_throttle_retry_policy.py
azure/cosmos/_retry_options.py
azure/cosmos/_retry_utility.py
azure/cosmos/_runtime_constants.py
azure/cosmos/_session.py
azure/cosmos/_session_retry_policy.py
azure/cosmos/_session_token_helpers.py
azure/cosmos/_synchronized_request.py
azure/cosmos/_timeout_failover_retry_policy.py
azure/cosmos/_utils.py
azure/cosmos/_vector_session_token.py
azure/cosmos/_version.py
azure/cosmos/auth.py
azure/cosmos/container.py
azure/cosmos/cosmos_client.py
azure/cosmos/database.py
azure/cosmos/diagnostics.py
azure/cosmos/documents.py
azure/cosmos/errors.py
azure/cosmos/exceptions.py
azure/cosmos/http_constants.py
azure/cosmos/offer.py
azure/cosmos/partition_key.py
azure/cosmos/permission.py
azure/cosmos/py.typed
azure/cosmos/scripts.py
azure/cosmos/user.py
azure/cosmos/_change_feed/__init__.py
azure/cosmos/_change_feed/change_feed_fetcher.py
azure/cosmos/_change_feed/change_feed_iterable.py
azure/cosmos/_change_feed/change_feed_start_from.py
azure/cosmos/_change_feed/change_feed_state.py
azure/cosmos/_change_feed/composite_continuation_token.py
azure/cosmos/_change_feed/feed_range_composite_continuation_token.py
azure/cosmos/_change_feed/feed_range_internal.py
azure/cosmos/_change_feed/aio/__init__.py
azure/cosmos/_change_feed/aio/change_feed_fetcher.py
azure_cosmos-4.9.0.dist-info/LICENSE
azure_cosmos-4.9.0.dist-info/METADATA
azure_cosmos-4.9.0.dist-info/WHEEL
azure_cosmos-4.9.0.dist-info/top_level.txt
azure_cosmos-4.9.0.dist-info/RECORD
